<item>
<title>[COLOR white][I][B][COLOR lime]»»[/COLOR]Episódio 1 [/I][/B][/COLOR]</title>
<link>http://localhost:65251/play?uri=magnet:?xt=urn:btih:28E0C8576BE98881F58FAEF6625F7B0CBAEBFD21</link>
<thumbnail>https://upload.wikimedia.org/wikipedia/en/thumb/a/a7/Westworld_Season_3.jpg/220px-Westworld_Season_3.jpg</thumbnail>
<info></info>
<fanart>https://upload.wikimedia.org/wikipedia/pt/4/41/Westworld_title_card.jpg</fanart>
</item>

<item>
<title>[COLOR white][I][B][COLOR lime]»»[/COLOR]Episódio 2 [/I][/B][/COLOR]</title>
<link>http://localhost:65251/play?uri=magnet:?xt=urn:btih:B85E33DB77BD73D5E3E1AFE8EDA818162235BD06</link>
<thumbnail>https://upload.wikimedia.org/wikipedia/en/thumb/a/a7/Westworld_Season_3.jpg/220px-Westworld_Season_3.jpg</thumbnail>
<info></info>
<fanart>https://upload.wikimedia.org/wikipedia/pt/4/41/Westworld_title_card.jpg</fanart>
</item>

<item>
<title>[COLOR white][I][B][COLOR lime]»»[/COLOR]Episódio 3 [/I][/B][/COLOR]</title>
<link>http://localhost:65251/play?uri=magnet:?xt=urn:btih:D7182883C550102B132F5B5C80AB32DC4490F22C</link>
<thumbnail>https://upload.wikimedia.org/wikipedia/en/thumb/a/a7/Westworld_Season_3.jpg/220px-Westworld_Season_3.jpg</thumbnail>
<info></info>
<fanart>https://upload.wikimedia.org/wikipedia/pt/4/41/Westworld_title_card.jpg</fanart>
</item>

<item>
<title>[COLOR white][I][B][COLOR lime]»»[/COLOR]Episódio 4 [/I][/B][/COLOR]</title>
<link>http://localhost:65251/play?uri=magnet:?xt=urn:btih:F3612F4A3A2BA532ADB8699248A0FC1812314D36</link>
<thumbnail>https://upload.wikimedia.org/wikipedia/en/thumb/a/a7/Westworld_Season_3.jpg/220px-Westworld_Season_3.jpg</thumbnail>
<info></info>
<fanart>https://upload.wikimedia.org/wikipedia/pt/4/41/Westworld_title_card.jpg</fanart>
</item>

<item>
<title>[COLOR white][I][B][COLOR lime]»»[/COLOR]Episódio 5 [/I][/B][/COLOR]</title>
<link>http://localhost:65251/play?uri=magnet:?xt=urn:btih:C3D6A36EA620EA85CEE7000B2320EEE094790456</link>
<thumbnail>https://upload.wikimedia.org/wikipedia/en/thumb/a/a7/Westworld_Season_3.jpg/220px-Westworld_Season_3.jpg</thumbnail>
<info></info>
<fanart>https://upload.wikimedia.org/wikipedia/pt/4/41/Westworld_title_card.jpg</fanart>
</item>


