<item>
<title>[COLOR white][I][B][COLOR lime]»»[/COLOR] 1ª Temporada [/I][/B][/COLOR]</title>
<link>http://ignorame</link>
<thumbnail>https://i.imgur.com/fORYBKg.jpg</thumbnail>
<fanart></fanart>
<externallink>https://raw.githubusercontent.com/asoryeslew/listas/master/S%C3%A9ries/Vikings/1%C2%AAtemporada.xml</externallink>
</item>

<item>
<title>[COLOR white][I][B][COLOR lime]»»[/COLOR] 2ª Temporada [/I][/B][/COLOR]</title>
<link>http://ignorame</link>
<thumbnail>https://i.imgur.com/qFbkMVs.jpg</thumbnail>
<fanart></fanart>
<externallink>https://raw.githubusercontent.com/asoryeslew/listas/master/S%C3%A9ries/Vikings/2%C2%AAtemporada.xml</externallink>
</item>